{
  "slug": "umwelt-energie-und-klimaschutz",
  "name": "Staatsministerium für Umwelt, Energie und Klimaschutz",
  "kurzname": "Umwelt und Energie",
  "leitung": "Staatsminister Tim Dieter",
  "teaser": "Das Ressort steuert Umweltpolitik, Energiefragen und Klimaschutz mit Blick auf Versorgungssicherheit und regionale Resilienz.",
  "aufgaben": [
    "Klimaschutz und Anpassung an Umwelt- und Wetterfolgen",
    "Energiepolitik und Begleitung des Strukturwandels",
    "Naturschutz, Ressourcenpolitik und ökologische Modernisierung"
  ],
  "kontakt": {
    "name": "Bürgerreferat Umwelt",
    "email": "umwelt@osten.de",
    "telefon": "+49 351 100-4200",
    "referat": "Referat Umwelt und Klima"
  },
  "bild": "/images/ministerien/ministerium-platzhalter.svg",
  "bildnachweis": "Illustrativer Platzhalter",
  "themen": [
    "Klimaschutz",
    "Energie",
    "Naturschutz"
  ],
  "verknuepfteLinks": [
    {
      "label": "Profil von Tim Dieter",
      "href": "/staatsregierung/mitglieder/tim-dieter/"
    },
    {
      "label": "Kontakt",
      "href": "/service/kontakt/"
    }
  ]
}
